AUTHORS
LICENSE
MANIFEST.in
README.rst
setup.cfg
setup.py
pywallet_lts/__init__.py
pywallet_lts/_version.py
pywallet_lts/network.py
pywallet_lts/wallet.py
pywallet_lts.egg-info/PKG-INFO
pywallet_lts.egg-info/SOURCES.txt
pywallet_lts.egg-info/dependency_links.txt
pywallet_lts.egg-info/requires.txt
pywallet_lts.egg-info/top_level.txt
pywallet_lts/utils/__init__.py
pywallet_lts/utils/bip32.py
pywallet_lts/utils/ethereum.py
pywallet_lts/utils/keys.py
pywallet_lts/utils/utils.py