Metadata-Version: 2.1
Name: pywallet-lts
Version: 0.1.1
Summary: Simple BIP32 (HD) wallet creation for BTC, BTG, BCH, LTC, DASH, USDT, QTUM and DOGE
Author: Lts
Author-email: nail.velichko2016@yandex.ru
License: MIT License
Keywords: bitcoin,wallet,litecoin,hd-wallet,dogecoin,dashcoin,python
Platform: any
Classifier: License :: OSI Approved :: MIT License
Classifier: Development Status :: 3 - Alpha
Classifier: Intended Audience :: Developers
Classifier: Operating System :: OS Independent
Classifier: Programming Language :: Python :: 3.10
License-File: LICENSE
License-File: AUTHORS
